mycroft_classic_listener/__init__.py
mycroft_classic_listener/__main__.py
mycroft_classic_listener/data_structures.py
mycroft_classic_listener/listener.py
mycroft_classic_listener/mic.py
mycroft_classic_listener/service.py
mycroft_classic_listener/version.py
mycroft_classic_listener/res/snd/acknowledge.mp3
mycroft_classic_listener/res/snd/error.mp3
mycroft_classic_listener/res/snd/start_listening.wav
mycroft_classic_listener-0.1.0.dist-info/LICENSE.md
mycroft_classic_listener-0.1.0.dist-info/METADATA
mycroft_classic_listener-0.1.0.dist-info/WHEEL
mycroft_classic_listener-0.1.0.dist-info/entry_points.txt
mycroft_classic_listener-0.1.0.dist-info/top_level.txt
mycroft_classic_listener-0.1.0.dist-info/RECORD
