Metadata-Version: 2.1
Name: mycroft-classic-listener
Version: 0.1.0
Summary: ovos-core listener daemon client
Home-page: https://github.com/OpenVoiceOS/mycroft-classic-listener
License: Apache-2.0
Classifier: Development Status :: 4 - Beta
Classifier: Programming Language :: Python :: 3
Classifier: License :: OSI Approved :: Apache Software License
License-File: LICENSE.md
Requires-Dist: SpeechRecognition>=3.8.1
Requires-Dist: PyAudio~=0.2
Requires-Dist: ovos-utils<1.0.0,>=0.7.0
Requires-Dist: ovos-bus-client<2.0.0,>=0.1.6
Requires-Dist: ovos-plugin-manager<1.0.0,>=0.8.3
Requires-Dist: ovos-config<2.0.0,>=0.4.6
